py2fa/__init__.py
py2fa/config.py
py2fa/py2fa.py
py2fa_cli-1.1.1.dist-info/LICENSE
py2fa_cli-1.1.1.dist-info/METADATA
py2fa_cli-1.1.1.dist-info/WHEEL
py2fa_cli-1.1.1.dist-info/entry_points.txt
py2fa_cli-1.1.1.dist-info/top_level.txt
py2fa_cli-1.1.1.dist-info/RECORD
