Metadata-Version: 2.1
Name: py2fa-cli
Version: 1.1.1
Summary: Command-line application for calculating one-time passwords for 2FA.
Author-email: arcctgx <arcctgx@o2.pl>
License: GPLv3
Project-URL: Homepage, https://github.com/arcctgx/py2fa-cli
Project-URL: Issues, https://github.com/arcctgx/py2fa-cli/issues
Classifier: Development Status :: 5 - Production/Stable
Classifier: Environment :: Console
Classifier: Intended Audience :: End Users/Desktop
Classifier: License :: OSI Approved :: GNU General Public License v3 (GPLv3)
Classifier: Natural Language :: English
Classifier: Programming Language :: Python :: 3 :: Only
Requires-Python: >=3.7
License-File: LICENSE
Requires-Dist: pyotp
Requires-Dist: pyxdg
